{
  "workload.attention_temperature": 1.0,
  "workload.enable_decoder_layer_norm": true,
  "workload.enable_residual_connections": true,
  "workload.eval_batch_size": 256,
  "workload.eval_period_time_sec": 1440,
  "workload.freq_mask_count": 2,
  "workload.layernorm_everywhere": false,
  "workload.max_allowed_runtime_sec": 55506,
  "workload.num_eval_train_examples": 5376,
  "workload.num_test_examples": 2472,
  "workload.num_train_examples": 263840,
  "workload.num_validation_examples": 5348,
  "workload.step_hint": 48000,
  "workload.target_metric_name": "wer",
  "workload.test_target_value": 0.07981,
  "workload.time_mask_count": 10,
  "workload.train_mean": 10,
  "workload.train_stddev": 10,
  "workload.use_gelu": false,
  "workload.use_post_layer_norm": true,
  "workload.use_specaug": true,
  "workload.use_tanh": true,
  "workload.validation_target_value": 0.133449,
  "cpu.util.avg_percent_since_last": 1.6,
  "cpu.freq.current": 2000.1760000000031,
  "mem.total": 253568368640,
  "mem.available": 244770471936,
  "mem.used": 6468358144,
  "mem.percent_used": 3.5,
  "mem.read_bytes_since_boot": 124780274176,
  "mem.write_bytes_since_boot": 9393432064,
  "net.bytes_sent_since_boot": 2051697,
  "net.bytes_recv_since_boot": 148437811,
  "gpu.count": 8,
  "gpu.0.compute.util": 0.2,
  "gpu.0.mem.util": 0.75982666015625,
  "gpu.0.mem.total": 16384.0,
  "gpu.0.mem.used": 12449.0,
  "gpu.0.mem.free": 3701.0,
  "gpu.0.temp.current": 35.0,
  "gpu.1.compute.util": 0.0,
  "gpu.1.mem.util": 0.75836181640625,
  "gpu.1.mem.total": 16384.0,
  "gpu.1.mem.used": 12425.0,
  "gpu.1.mem.free": 3725.0,
  "gpu.1.temp.current": 35.0,
  "gpu.2.compute.util": 0.0,
  "gpu.2.mem.util": 0.75836181640625,
  "gpu.2.mem.total": 16384.0,
  "gpu.2.mem.used": 12425.0,
  "gpu.2.mem.free": 3725.0,
  "gpu.2.temp.current": 38.0,
  "gpu.3.compute.util": 0.0,
  "gpu.3.mem.util": 0.75836181640625,
  "gpu.3.mem.total": 16384.0,
  "gpu.3.mem.used": 12425.0,
  "gpu.3.mem.free": 3725.0,
  "gpu.3.temp.current": 36.0,
  "gpu.4.compute.util": 0.13,
  "gpu.4.mem.util": 0.75836181640625,
  "gpu.4.mem.total": 16384.0,
  "gpu.4.mem.used": 12425.0,
  "gpu.4.mem.free": 3725.0,
  "gpu.4.temp.current": 34.0,
  "gpu.5.compute.util": 0.0,
  "gpu.5.mem.util": 0.75836181640625,
  "gpu.5.mem.total": 16384.0,
  "gpu.5.mem.used": 12425.0,
  "gpu.5.mem.free": 3725.0,
  "gpu.5.temp.current": 37.0,
  "gpu.6.compute.util": 0.13,
  "gpu.6.mem.util": 0.75836181640625,
  "gpu.6.mem.total": 16384.0,
  "gpu.6.mem.used": 12425.0,
  "gpu.6.mem.free": 3725.0,
  "gpu.6.temp.current": 37.0,
  "gpu.7.compute.util": 0.12,
  "gpu.7.mem.util": 0.75836181640625,
  "gpu.7.mem.total": 16384.0,
  "gpu.7.mem.used": 12425.0,
  "gpu.7.mem.free": 3725.0,
  "gpu.7.temp.current": 38.0,
  "gpu.avg.compute.util": 0.07250000000000001,
  "gpu.avg.mem.util": 0.758544921875,
  "gpu.avg.mem.total": 16384.0,
  "gpu.avg.mem.used": 12428.0,
  "gpu.avg.mem.free": 3722.0,
  "gpu.avg.temp.current": 36.25,
  "os_platform": "Linux-4.19.0-26-cloud-amd64-x86_64-with-glibc2.29",
  "python_version": "3.8.10",
  "python_compiler": "GCC 9.4.0",
  "cpu_model_name": "Intel(R) Xeon(R) CPU @ 2.00GHz",
  "cpu_count": 64,
  "gpu_model_name": "Tesla V100-SXM2-16GB",
  "gpu_count": 8,
  "gpu_driver": "535.104.05",
  "rng_seed": 1884662704
}