{
  "workload.bn_init_scale": 0.0,
  "workload.center_crop_size": 224,
  "workload.eval_batch_size": 1024,
  "workload.eval_period_time_sec": 510,
  "workload.max_allowed_runtime_sec": 63008,
  "workload.num_eval_train_examples": 50176,
  "workload.num_test_examples": 10000,
  "workload.num_train_examples": 1281167,
  "workload.num_validation_examples": 50000,
  "workload.resize_size": 256,
  "workload.step_hint": 186666,
  "workload.target_metric_name": "accuracy",
  "workload.test_target_value": 0.656,
  "workload.use_gelu": false,
  "workload.use_silu": false,
  "workload.validation_target_value": 0.77431,
  "cpu.util.avg_percent_since_last": 42.0,
  "cpu.freq.current": 2000.1279999999979,
  "mem.total": 253568368640,
  "mem.available": 52831723520,
  "mem.used": 196827332608,
  "mem.percent_used": 79.2,
  "mem.read_bytes_since_boot": 19912946799104,
  "mem.write_bytes_since_boot": 13967906304,
  "net.bytes_sent_since_boot": 710980,
  "net.bytes_recv_since_boot": 1586511,
  "gpu.count": 8,
  "gpu.0.compute.util": 0.0,
  "gpu.0.mem.util": 0.79058837890625,
  "gpu.0.mem.total": 16384.0,
  "gpu.0.mem.used": 12953.0,
  "gpu.0.mem.free": 3197.0,
  "gpu.0.temp.current": 42.0,
  "gpu.1.compute.util": 0.0,
  "gpu.1.mem.util": 0.78826904296875,
  "gpu.1.mem.total": 16384.0,
  "gpu.1.mem.used": 12915.0,
  "gpu.1.mem.free": 3235.0,
  "gpu.1.temp.current": 41.0,
  "gpu.2.compute.util": 0.0,
  "gpu.2.mem.util": 0.79205322265625,
  "gpu.2.mem.total": 16384.0,
  "gpu.2.mem.used": 12977.0,
  "gpu.2.mem.free": 3173.0,
  "gpu.2.temp.current": 47.0,
  "gpu.3.compute.util": 0.0,
  "gpu.3.mem.util": 0.79193115234375,
  "gpu.3.mem.total": 16384.0,
  "gpu.3.mem.used": 12975.0,
  "gpu.3.mem.free": 3175.0,
  "gpu.3.temp.current": 45.0,
  "gpu.4.compute.util": 0.0,
  "gpu.4.mem.util": 0.79193115234375,
  "gpu.4.mem.total": 16384.0,
  "gpu.4.mem.used": 12975.0,
  "gpu.4.mem.free": 3175.0,
  "gpu.4.temp.current": 41.0,
  "gpu.5.compute.util": 0.0,
  "gpu.5.mem.util": 0.78839111328125,
  "gpu.5.mem.total": 16384.0,
  "gpu.5.mem.used": 12917.0,
  "gpu.5.mem.free": 3233.0,
  "gpu.5.temp.current": 45.0,
  "gpu.6.compute.util": 0.0,
  "gpu.6.mem.util": 0.79193115234375,
  "gpu.6.mem.total": 16384.0,
  "gpu.6.mem.used": 12975.0,
  "gpu.6.mem.free": 3175.0,
  "gpu.6.temp.current": 47.0,
  "gpu.7.compute.util": 0.0,
  "gpu.7.mem.util": 0.79205322265625,
  "gpu.7.mem.total": 16384.0,
  "gpu.7.mem.used": 12977.0,
  "gpu.7.mem.free": 3173.0,
  "gpu.7.temp.current": 47.0,
  "gpu.avg.compute.util": 0.0,
  "gpu.avg.mem.util": 0.7908935546875,
  "gpu.avg.mem.total": 16384.0,
  "gpu.avg.mem.used": 12958.0,
  "gpu.avg.mem.free": 3192.0,
  "gpu.avg.temp.current": 44.375,
  "os_platform": "Linux-4.19.0-26-cloud-amd64-x86_64-with-glibc2.29",
  "python_version": "3.8.10",
  "python_compiler": "GCC 9.4.0",
  "cpu_model_name": "Intel(R) Xeon(R) CPU @ 2.00GHz",
  "cpu_count": 64,
  "gpu_model_name": "Tesla V100-SXM2-16GB",
  "gpu_count": 8,
  "gpu_driver": "535.104.05",
  "rng_seed": 485521238
}